{
  "dataset": "demo",
  "model": "lstm",
  "run_name": "lstm_baseline",
  "checkpoint": "checkpoints\\demo_lstm_best.pt",
  "overall": {
    "mae": 2.2904653549194336,
    "rmse": 2.872119426727295,
    "mape_percent": 8.641460418701172
  },
  "per_horizon": [
    {
      "horizon": 1,
      "mae": 2.072929620742798,
      "rmse": 2.588813066482544,
      "mape_percent": 8.409139633178711
    },
    {
      "horizon": 2,
      "mae": 2.036562919616699,
      "rmse": 2.537795305252075,
      "mape_percent": 8.109073638916016
    },
    {
      "horizon": 3,
      "mae": 2.0917677879333496,
      "rmse": 2.60178542137146,
      "mape_percent": 8.25678539276123
    },
    {
      "horizon": 4,
      "mae": 2.042642116546631,
      "rmse": 2.542262077331543,
      "mape_percent": 7.841058731079102
    },
    {
      "horizon": 5,
      "mae": 2.1549088954925537,
      "rmse": 2.6728782653808594,
      "mape_percent": 8.275362968444824
    },
    {
      "horizon": 6,
      "mae": 2.1627278327941895,
      "rmse": 2.6910858154296875,
      "mape_percent": 8.059600830078125
    },
    {
      "horizon": 7,
      "mae": 2.234198570251465,
      "rmse": 2.7892396450042725,
      "mape_percent": 8.214070320129395
    },
    {
      "horizon": 8,
      "mae": 2.342803478240967,
      "rmse": 2.9225528240203857,
      "mape_percent": 8.644140243530273
    },
    {
      "horizon": 9,
      "mae": 2.4353561401367188,
      "rmse": 3.0451176166534424,
      "mape_percent": 8.983648300170898
    },
    {
      "horizon": 10,
      "mae": 2.498561143875122,
      "rmse": 3.1393821239471436,
      "mape_percent": 9.097545623779297
    },
    {
      "horizon": 11,
      "mae": 2.6525161266326904,
      "rmse": 3.305032253265381,
      "mape_percent": 9.730634689331055
    },
    {
      "horizon": 12,
      "mae": 2.760608673095703,
      "rmse": 3.4431092739105225,
      "mape_percent": 10.07646369934082
    }
  ]
}